enmailer/__init__.py
enmailer/enmailer.py
enmailer/error.py
enmailer-1.0.0.dist-info/METADATA
enmailer-1.0.0.dist-info/WHEEL
enmailer-1.0.0.dist-info/top_level.txt
enmailer-1.0.0.dist-info/RECORD
