Metadata-Version: 2.1
Name: enmailer
Version: 1.0.0
Summary: Evernote Email Sender
Home-page: https://github.com/chiantiscarlett/evernote-mailer
Author: Chianti Scarlett
Author-email: chianti.scarlett@gmail.com
License: UNKNOWN
Platform: UNKNOWN
Classifier: Development Status :: 3 - Alpha
Classifier: Programming Language :: Python :: 3
